setup.cfg
setup.py
gtwisted/__init__.py
gtwisted.egg-info/PKG-INFO
gtwisted.egg-info/SOURCES.txt
gtwisted.egg-info/dependency_links.txt
gtwisted.egg-info/entry_points.txt
gtwisted.egg-info/not-zip-safe
gtwisted.egg-info/requires.txt
gtwisted.egg-info/top_level.txt
gtwisted/core/__init__.py
gtwisted/core/asyncaller.py
gtwisted/core/asyncresultfactory.py
gtwisted/core/base.py
gtwisted/core/basereactor.py
gtwisted/core/error.py
gtwisted/core/greactor.py
gtwisted/core/greenlets.py
gtwisted/core/installer.py
gtwisted/core/protocols.py
gtwisted/core/rpc.py
gtwisted/test/__init__.py
gtwisted/test/http_test.py
gtwisted/test/pbclient_test.py
gtwisted/test/pbserver_test.py
gtwisted/test/test.py
gtwisted/test/test1.py
gtwisted/test/test_netconnect_client.py
gtwisted/test/test_netconnect_server.py
gtwisted/test/twisted_test.py
gtwisted/utils/__init__.py
gtwisted/utils/context.py
gtwisted/utils/failure.py
gtwisted/utils/log.py
gtwisted/utils/output.py
gtwisted/utils/reflect.py
gtwisted/utils/singleton.py
gtwisted/utils/version.py