Metadata-Version: 1.0
Name: gtwisted
Version: 0.2.8alpha
Summary: Achieve twisted based on gevent
Home-page: http://www.9miao.com/
Author: lanjinmin
Author-email: zhuiming.mu@gmail.com
License: MIT
Keywords: gevent twisted pb
Platform: UNKNOWN
